COPYING
MANIFEST.in
README.rst
requirements.txt
setup.cfg
setup.py
doc/Makefile
doc/conf.py
doc/domain.rst
doc/fibre.rst
doc/gaussian.rst
doc/index.rst
doc/installation.rst
doc/overview.rst
doc/reference.rst
doc/system.rst
doc/tutorial.rst
examples/README
examples/run_examples.py
examples/agrawal_book/fig_3-1.py
examples/agrawal_book/fig_3-3.py
examples/agrawal_book/fig_3-4.py
examples/agrawal_book/fig_3-6.py
examples/agrawal_book/fig_3-7.py
examples/agrawal_book/fig_4-11.py
examples/agrawal_book/fig_4-12.py
examples/agrawal_book/fig_4-13.py
examples/agrawal_book/fig_4-15.py
examples/agrawal_book/fig_4-16.py
examples/agrawal_book/fig_4-19.py
examples/agrawal_book/fig_4-20.py
examples/agrawal_book/fig_4-21.py
examples/agrawal_book/fig_4-23.py
examples/agrawal_book/fig_4-4.py
examples/agrawal_book/fig_4-5.py
examples/agrawal_book/fig_4-8.py
examples/agrawal_book/fig_4-9.py
examples/agrawal_book/fig_5-16a.py
examples/agrawal_book/fig_5-16b.py
examples/agrawal_book/fig_5-16c.py
examples/agrawal_book/fig_5-16d.py
examples/agrawal_book/fig_5-17.py
examples/agrawal_book/fig_5-18.py
examples/agrawal_book/fig_5-19.py
examples/agrawal_book/fig_5-21.py
examples/agrawal_book/fig_5-23.py
examples/agrawal_book/fig_5-6.py
examples/agrawal_book/fig_5-8.py
examples/agrawal_book/fig_5-9.py
examples/agrawal_book/fig_7-2.py
examples/agrawal_book/fig_7-6.py
examples/agrawal_book/fig_7-7.py
examples/agrawal_book/fig_7-8.py
examples/agrawal_book/fig_7-9.py
examples/second_order_soliton/soliton.py
examples/second_order_soliton/soliton_adaptive.py
examples/soliton_collision/soliton_collision.py
examples/verification/frequency_and_wavelength.py
examples/verification/gaussian_various_parameters.py
pyofss/__init__.py
pyofss/domain.py
pyofss/field.py
pyofss/metrics.py
pyofss/system.py
pyofss.egg-info/PKG-INFO
pyofss.egg-info/SOURCES.txt
pyofss.egg-info/dependency_links.txt
pyofss.egg-info/requires.txt
pyofss.egg-info/top_level.txt
pyofss/modules/__init__.py
pyofss/modules/amplifier.py
pyofss/modules/bit.py
pyofss/modules/cw.py
pyofss/modules/fibre.py
pyofss/modules/filter.py
pyofss/modules/gaussian.py
pyofss/modules/generator.py
