Metadata-Version: 1.1
Name: pyofss
Version: 0.9
Summary: Optical fibre system simulator
Home-page: http://curvedthoughts.com/pyofss
Author: David Bolt (daibo)
Author-email: djb@curvedthoughts.com
License: GNU GPL
Download-URL: http://pypi.python.org/pypi/pyofss
Keywords: photonic,simulation,fiber,fibre,optical
Platform: POSIX
Classifier: Development Status :: 5 - Production/Stable
Classifier: Environment :: Console
Classifier: Intended Audience :: Science/Research
Classifier: License :: OSI Approved :: GNU General Public License v3 (GPLv3)
Classifier: Natural Language :: English
Classifier: Operating System :: POSIX :: Linux
Classifier: Programming Language :: Python
Classifier: Programming Language :: Python :: 2.6
Classifier: Programming Language :: Python :: 2.7
Classifier: Topic :: Scientific/Engineering :: Physics
